smyg/__init__.py
smyg/__main__.py
smyg/binding.py
smyg/cli.py
smyg/formatter.py
smyg/metrics/code_changes.py
smyg/metrics/code_churn.py
smyg/prom.py
smyg/templates/code_changes.j2
smyg/templates/commit.j2
smyg/templates/commits.j2
smyg/utils.py
smyg/vcs.py
smyg-0.5.5.dist-info/METADATA
smyg-0.5.5.dist-info/WHEEL
smyg-0.5.5.dist-info/entry_points.txt
smyg-0.5.5.dist-info/LICENSE
smyg-0.5.5.dist-info/RECORD
