Metadata-Version: 2.1
Name: smyg
Version: 0.5.5
Summary: git metric calculation
Home-page: https://github.com/nmix/showmeyourgit
License: MIT
Keywords: git,metrics
Author: Nikolay Mikhaylichenko
Author-email: nn.mikh@yandex.ru
Requires-Python: >=3.7.2,<4.0.0
Classifier: License :: OSI Approved :: MIT License
Classifier: Operating System :: OS Independent
Classifier: Programming Language :: Python :: 3
Classifier: Programming Language :: Python :: 3.8
Classifier: Programming Language :: Python :: 3.9
Classifier: Programming Language :: Python :: 3.10
Classifier: Programming Language :: Python :: 3.11
Classifier: Programming Language :: Python :: 3
Requires-Dist: jinja2 (>=3.1.2,<4.0.0)
Requires-Dist: prometheus-client (>=0.16,<0.17)
Requires-Dist: pydriller (>=2.3,<3.0)
Requires-Dist: python-dateutil (>=2.8.2,<3.0.0)
Requires-Dist: rich (>=13.1.0,<14.0.0)
Requires-Dist: typer (>=0.7.0,<0.8.0)
Project-URL: Repository, https://github.com/nmix/showmeyourgit
